odoo/addons/l10n_et_hr/README.rst
odoo/addons/l10n_et_hr/__init__.py
odoo/addons/l10n_et_hr/__manifest__.py
odoo/addons/l10n_et_hr/models/__init__.py
odoo/addons/l10n_et_hr/models/hr_department.py
odoo/addons/l10n_et_hr/models/hr_employee.py
odoo/addons/l10n_et_hr/models/hr_employee_base.py
odoo/addons/l10n_et_hr/models/hr_employee_public.py
odoo/addons/l10n_et_hr/models/hr_job.py
odoo/addons/l10n_et_hr/models/res_config_settings.py
odoo/addons/l10n_et_hr/readme/CREDITS.rst
odoo/addons/l10n_et_hr/readme/DESCRIPTION.rst
odoo/addons/l10n_et_hr/static/description/icon.png
odoo/addons/l10n_et_hr/static/description/index.html
odoo/addons/l10n_et_hr/tests/__init__.py
odoo/addons/l10n_et_hr/tests/test_hr.py
odoo/addons/l10n_et_hr/views/hr_employee_public_views.xml
odoo/addons/l10n_et_hr/views/hr_employee_views.xml
odoo/addons/l10n_et_hr/views/res_config_settings_views.xml
odoo14_addon_l10n_et_hr-14.0.1.0.1.dev4.dist-info/METADATA
odoo14_addon_l10n_et_hr-14.0.1.0.1.dev4.dist-info/WHEEL
odoo14_addon_l10n_et_hr-14.0.1.0.1.dev4.dist-info/top_level.txt
odoo14_addon_l10n_et_hr-14.0.1.0.1.dev4.dist-info/RECORD
